hetzner_set_dns_txt_record/__init__.py
hetzner_set_dns_txt_record/api.py
hetzner_set_dns_txt_record-0.2.2.data/scripts/hetzner_set_dns_txt.py
hetzner_set_dns_txt_record-0.2.2.dist-info/LICENSE.md
hetzner_set_dns_txt_record-0.2.2.dist-info/METADATA
hetzner_set_dns_txt_record-0.2.2.dist-info/WHEEL
hetzner_set_dns_txt_record-0.2.2.dist-info/top_level.txt
hetzner_set_dns_txt_record-0.2.2.dist-info/RECORD
