Metadata-Version: 2.1
Name: hetzner-set-dns-txt-record
Version: 0.2.2
Summary: A script to change DNS TXT records in the Hetzner robot
Home-page: https://github.com/neuroforgede/hetzner_set_dns_txt_record
Author: NeuroForge GmbH & Co. KG
Author-email: github@neuroforge.de
License: GNU Affero General Public License
Platform: UNKNOWN
Requires-Python: >=3.6
Requires-Dist: beautifulsoup4 (>=4.8.2)
Requires-Dist: requests (>=2.22.0)
Requires-Dist: easyzone3 (==1.2.3)
